odoo/addons/sale_order_min_qty/README.rst
odoo/addons/sale_order_min_qty/__init__.py
odoo/addons/sale_order_min_qty/__manifest__.py
odoo/addons/sale_order_min_qty/i18n/ca.po
odoo/addons/sale_order_min_qty/i18n/es.po
odoo/addons/sale_order_min_qty/i18n/sale_order_min_qty.pot
odoo/addons/sale_order_min_qty/models/__init__.py
odoo/addons/sale_order_min_qty/models/product.py
odoo/addons/sale_order_min_qty/models/sale.py
odoo/addons/sale_order_min_qty/readme/CONTRIBUTORS.rst
odoo/addons/sale_order_min_qty/readme/DESCRIPTION.rst
odoo/addons/sale_order_min_qty/readme/USAGE.rst
odoo/addons/sale_order_min_qty/static/description/icon.png
odoo/addons/sale_order_min_qty/static/description/index.html
odoo/addons/sale_order_min_qty/tests/__init__.py
odoo/addons/sale_order_min_qty/tests/test_sale.py
odoo/addons/sale_order_min_qty/views/product_views.xml
odoo/addons/sale_order_min_qty/views/sale_views.xml
odoo12_addon_sale_order_min_qty-12.0.1.0.0.99.dev15.dist-info/METADATA
odoo12_addon_sale_order_min_qty-12.0.1.0.0.99.dev15.dist-info/WHEEL
odoo12_addon_sale_order_min_qty-12.0.1.0.0.99.dev15.dist-info/top_level.txt
odoo12_addon_sale_order_min_qty-12.0.1.0.0.99.dev15.dist-info/RECORD
